extra/verilog/mem.sv
module mem #(
    // This fancy hashtag thingy lets me put an INIT file into the mem
    parameter INIT = ""
)(
    input logic clk,
    input logic rst,
    input logic we,
    input logic [15:0] addr,
    input logic [31:0] write_data,
    output logic [31:0] read_data
);
    localparam SIZE = 2**16;

    logic [31:0] RAM [SIZE];

    // Load from Init ROM, if it exists
    initial begin
        // First, zero everything out (INIT ROM might not fill entire ROM)

        for (int i = 0; i < SIZE; i++) begin
            RAM[i] = '0;
        end

        if (INIT != "") begin
            $readmemh(INIT, RAM);
        end
    end

    always_ff @(posedge clk) begin
        if (we) begin
            RAM[addr] <= write_data;
        end
    end

    assign read_data = RAM[addr];

endmodule

extra/verilog/alu.sv
import types::*;

module alu(
    input logic [31:0] a,
    input logic [31:0] b,
    input operation op,
    output logic [31:0] out
);
    always_comb begin 
        case(op)
            ADD: out = $signed($signed(a) + $signed(b));
            SUB: out = $signed($signed(a) - $signed(b));
            NAND: out = ~(a & b);
            ADD1: out = a + 1;
            PASSA: out = a;
            PASSB: out = b;
            IGNORE: out = 'X;
            default: out = 'X;
            // Triggers error if non-defined code 
        endcase
    end

endmodule

extra/verilog/dprf.sv
module dprf(
    input logic clk,
    input logic rst,
    input logic we,
    input logic [3:0] regno_read1,
    input logic [3:0] regno_read2,
    input logic [3:0] regno_write,
    input logic [31:0] write_data,
    output logic [31:0] read_data1,
    output logic [31:0] read_data2
);
    localparam NUM_REG = 16;

    // 16 registers, each 32 bits
    logic [31:0] registers [NUM_REG];

    always_ff @(posedge clk) begin
        if (rst) begin
            // Clear all registers
            for (int i = 0; i < NUM_REG; i++) begin
                registers[i] <= '0;
            end
        end else if (we && regno_write != 4'd0) begin
            // If Write_Enable and not $zero, write
            registers[regno_write] <= write_data;
        end
    end

    function logic [31:0] read_port(input logic [3:0] regno);
        if (regno == 4'd0) begin
            return '0; // Force to 0 in case of bad initialization
        end else if (we && (regno_write == regno)) begin
            return write_data; // Port Forwarding
        end else begin
            return registers[regno];
        end
    endfunction

    assign read_data1 = read_port(regno_read1); 
    assign read_data2 = read_port(regno_read2);

endmodule

extra/verilog/pipeline.sv
import types::*;

module pipeline(
    input logic clk,
    input logic rst
);

// Everything is defined left to right

// ************ //
// GLOBAL LOGIC //
// ************ //

logic [31:0] PC;

logic stall_now;

logic branch_true;
logic [31:0] branch_target_line;

logic [3:0] write_reg_dest;
logic [31:0] write_reg_data;


fbuf_data fbuf_in, fbuf_out;
dbuf_data dbuf_in, dbuf_out;
ebuf_data ebuf_in, ebuf_out;
mbuf_data mbuf_in, mbuf_out;

always_ff @(posedge clk) begin
    if (rst) begin
        stall_now <= 1'b0;
    end else if (dbuf_out.opcode == OP_HALT) begin
        // As soon as we get HALT in the exec stage,
        // latch onto the STALL forever and forever.
        stall_now <= 1'b1;
    end

    if (rst) begin
        PC <= 32'd0;
    end else if (!stall_now) begin
        // We ONLY want to change PC if we're not Stalled
        PC <= branch_true? branch_target_line : (PC + 1);
    end
end


// *********** //
// FETCH STAGE //
// *********** //

// This wire is the output from imem
logic [31:0] instruction_read_line;

mem #(.INIT("../pow.hex")) imem (
    .clk(clk),
    .rst(rst),
    .we(1'b0),
    .addr(PC[15:0]),
    .write_data('0),
    .read_data(instruction_read_line)
);

always_comb begin
    fbuf_in.pc_plus_1 = PC + 1;
    fbuf_in.instruction = instruction_read_line;
end

always_ff @(posedge clk) begin
    // If Stalled,
    // then we can't forward our newly fetched instruction to the Decode Stage
    if (!stall_now) begin
        fbuf_out <= (rst || branch_true) ? '0 : fbuf_in;
    end
end


// ************ //
// DECODE STAGE //
// ************ //

instruction_data ins;
assign ins = (rst || branch_true || stall_now) ? '0 : fbuf_out.instruction;
// Create Bubble (NOOP) when branch taken or stalled

logic is_immediate;

// sr1 and sr2 are the input registers for the DPRF
// and dout1 and dout2 are the output ports for them
// these douts will then be forwarded as the inputs to the ALU
// dr is just the desination register,
// which'll be forwarded to the memory stage
logic [3:0] dr, sr1, sr2; 
logic [31:0] dout1, dout2;

always_comb begin
    // This is for remaping which registers are:
    // 1. Desination Register (the one we write to)
    // 2. Source Registers (the ones whose data we need)
    //
    // Since we can read 2 things at once,
    // but can only write to 1 thing at a time...
    case (ins.opcode)
        // Ok, this is hardcoded,
        // but I just don't care...
        // lol I probably shouldn't say that
        
        // R-Type Instructions
        OP_ADD, OP_NAND, OP_MIN, OP_MAX: begin
            dr = ins.rx;
            sr1 = ins.ry;
            sr2 = ins.imm.rz;
        end 

        // if we didn't execute the previous block, then: //
        // IMMEDIATE INSTRUCTIONS //
        
        // I-Type with RX as DR.
        OP_ADDI, OP_LW: begin
            dr = ins.rx;
            sr1 = ins.ry;
            sr2 = '0; // unused
        end

        OP_JALR: begin
            dr = ins.ry;
            sr1 = ins.rx;
            sr2 = '0; // unused
        end

        // I-Type with 2 Sources (no DR)
        OP_SW, OP_BEQ, OP_BGT: begin
            // BEQ and BGT will compare the result,
            // And SW needs to read RX,
            // but will only use RY + OFFSET on the ALU
            dr = '0; // unused
            sr1 = ins.rx; 
            sr2 = ins.ry;
        end

        OP_LEA: begin
            dr = ins.rx;
            sr1 = '0;
            sr2 = '0;
        end

        OP_HALT: begin
            dr = '0;
            sr1 = '0;
            sr2 = '0;
        end

        // If we didn't explicitly set an instruction, FAIL
        // So that we know we forgot to implement something...
        default: begin
            dr = 'X;
            sr1 = 'X;
            sr2 = 'X;
        end
    endcase
end

// Physically instantiate and read/write registers
dprf registers (
    .clk(clk),
    .rst(rst),
    .we('1),
    .regno_read1(sr1),
    .regno_read2(sr2),
    .regno_write(write_reg_dest),
    .write_data(write_reg_data),
    .read_data1(dout1),
    .read_data2(dout2)
);


logic [19:0] imm_wire;

always_comb begin
    // Pass everything important along and let the EXECUTE Stage figure out
    // what it wants to do with our stuff
    dbuf_in.pc_plus_1 = fbuf_out.pc_plus_1;
    dbuf_in.opcode = ins.opcode;
    dbuf_in.dr = dr;

    // So... we need to do Data Forwarding
    // But ummm.... as of the time I'm writing, I'm too tired to modularize
    // So, remember to copy and paste and edit properly!!!
    dbuf_in.val1 = dout1;
    dbuf_in.sr1 = sr1;

    dbuf_in.val2 = dout2;
    dbuf_in.sr2 = sr2;

    imm_wire = ins.imm;

    dbuf_in.offset = { {12{imm_wire[19]}}, imm_wire };
end

always_ff @(posedge clk) begin
    dbuf_out <= (rst || stall_now || (dbuf_out.opcode == OP_HALT)) ? '0 : dbuf_in;
end

// DEBUGGGING //
logic [31:0] debug_dbuf_pc;     assign debug_dbuf_pc     = dbuf_out.pc_plus_1;
opcode_t     debug_dbuf_op;     assign debug_dbuf_op     = dbuf_out.opcode;
logic [3:0]  debug_dbuf_dr;     assign debug_dbuf_dr     = dbuf_out.dr;
logic [31:0] debug_dbuf_val1;   assign debug_dbuf_val1   = dbuf_out.val1;
logic [31:0] debug_dbuf_val2;   assign debug_dbuf_val2   = dbuf_out.val2;
logic [31:0] debug_dbuf_offset; assign debug_dbuf_offset = dbuf_out.offset;

// ************* //
// EXECUTE STAGE //
// ************* //


operation aluop;
logic [31:0] alu_val1;
logic [31:0] alu_val2;
logic [31:0] alu_result;

// We need to calculate the forwarded values
// And we might overwrite the alu_val's
// But then use the forwarded values later / elsewhere (like in SW)
// So, we need to keep these separate.
logic [31:0] fwd_val1;
logic [31:0] fwd_val2;

always_comb begin
    fwd_val1 = dbuf_out.val1;
    fwd_val2 = dbuf_out.val2;
    
    // 1. Check Results of Memory Stage First (older data, so lower priority)
    if ((mbuf_out.dr != 4'd0) && (mbuf_out.dr == dbuf_out.sr1)) begin
        fwd_val1 = mbuf_out.data;
    end
    if ((mbuf_out.dr != 4'd0) && (mbuf_out.dr == dbuf_out.sr2)) begin
        fwd_val2 = mbuf_out.data;
    end

    // 2. Check Results of Execute Stage Second (newer data, so higher priority)
    // Overwrites any forwarding from the memory stage
    if ((ebuf_out.dr != 4'd0) && (ebuf_out.dr == dbuf_out.sr1)) begin
        fwd_val1 = ebuf_out.data;
    end
    if ((ebuf_out.dr != 4'd0) && (ebuf_out.dr == dbuf_out.sr2)) begin
        fwd_val2 = ebuf_out.data;
    end

    alu_val1 = fwd_val1;
    alu_val2 = fwd_val2;


    case (dbuf_out.opcode)
        OP_ADD, OP_JALR: begin
            aluop = ADD;
        end

        OP_ADDI, OP_LW: begin
            aluop = ADD;
            alu_val2 = dbuf_out.offset;
        end

        OP_SW: begin
            aluop = ADD;
            alu_val1 = dbuf_out.offset;
        end

        OP_NAND: begin
            aluop = NAND;
        end

        OP_BEQ, OP_BGT, OP_MIN, OP_MAX: begin
            aluop = SUB; 
        end

        OP_HALT: begin
            aluop = IGNORE;
        end

        OP_LEA: begin
            aluop= ADD;
            alu_val1 = dbuf_out.pc_plus_1;
            alu_val2 = dbuf_out.offset;
        end

        default: begin
            aluop = IGNORE;
        end
    endcase
end

alu alu0 (
    .a(alu_val1),
    .b(alu_val2),
    .op(aluop),
    .out(alu_result)
);

always_comb begin
    branch_true = 1'b0;
    branch_target_line = dbuf_out.pc_plus_1 + dbuf_out.offset;
    
    ebuf_in.opcode = dbuf_out.opcode;

    ebuf_in.dr = '0;
    ebuf_in.address = '0;
    ebuf_in.data = '0;
    
    case (dbuf_out.opcode)
        OP_ADD, OP_NAND, OP_ADDI, OP_LEA: begin
            ebuf_in.dr = dbuf_out.dr;
            ebuf_in.data = alu_result;
        end

        OP_LW: begin
            ebuf_in.dr = dbuf_out.dr;
            ebuf_in.address = alu_result;
        end

        OP_SW: begin
            ebuf_in.address = alu_result;
            ebuf_in.data = fwd_val1;
        end

        OP_BEQ: begin
            branch_true = (alu_result == 0);
        end

        OP_JALR: begin
            ebuf_in.dr = dbuf_out.dr;
            ebuf_in.data = dbuf_out.pc_plus_1;
            branch_target_line = alu_result;
            branch_true = 1'b1;
        end

        OP_BGT: begin
            branch_true = ($signed(alu_result) > 0);
        end

        OP_MIN: begin
            ebuf_in.dr = dbuf_out.dr;
            ebuf_in.data = ($signed(alu_result) < 0) ? fwd_val1 : fwd_val2;
        end
        
        OP_MAX: begin
            ebuf_in.dr = dbuf_out.dr;
            ebuf_in.data = ($signed(alu_result) > 0) ? fwd_val1 : fwd_val2;
        end

    endcase
end

always_ff @(posedge clk) begin
    ebuf_out <= rst ? '0 : ebuf_in;
end

// ********* //
// MEM STAGE //
// ********* //

logic we_dmem;
logic [31:0] data_read_line;
logic [31:0] data_write_dmem;

always_comb begin
    we_dmem = (ebuf_out.opcode == OP_SW);
    data_write_dmem = ebuf_out.data;
end

mem #(.INIT("../pow.hex")) dmem (
    .clk(clk),
    .rst(rst),
    .we(we_dmem),
    .addr(ebuf_out.address[15:0]),
    .write_data(data_write_dmem),
    .read_data(data_read_line)
);

always_comb begin
    mbuf_in.dr = ebuf_out.dr;
    mbuf_in.data = '0;

    case (ebuf_out.opcode)
        OP_ADD, OP_NAND, OP_ADDI, OP_JALR, OP_LEA, OP_MIN, OP_MAX: begin
            mbuf_in.data = ebuf_out.data;
        end

        OP_LW: begin
            mbuf_in.data = data_read_line;
        end

        default: begin
            // SW, BEQ, HALT, BGT 
            mbuf_in.dr = '0;
            // Just in case...
        end
    endcase
end

always_ff @(posedge clk) begin
    mbuf_out <= rst? '0 : mbuf_in;
end

// **************** //
// WRITE BACK STAGE //
// **************** //

always_comb begin
   write_reg_dest = mbuf_out.dr;
   write_reg_data = mbuf_out.data;
end

endmodule

extra/verilog/test.sv
module test;
    logic clk;
    logic rst;

    pipeline dut (
        .clk(clk),
        .rst(rst)
    );

    // Clock oscillates every 5 time units, so clock cycle = 10 time units.
    always #5 clk = ~clk;

    initial begin
        // Record here
        $dumpfile("waves.vcd"); 
        $dumpvars(0, test);

        // By default, the registers are not dumped on a wire
        // And the testing software only dumps the outputs of wires onto the
        // waves file, I guess because we could have like infinite registers,
        // which would overload our stuff.
        // So... we have to manually dump the things we want
        for (int i = 0; i < 16; i++) begin
            $dumpvars(0, dut.registers.registers[i]);
        end

        
        // $dumpvars(0, dut.dbuf_out.pc_plus_1);
        // $dumpvars(0, dut.dbuf_out.opcode);
        // $dumpvars(0, dut.dbuf_out.dr);
        // $dumpvars(0, dut.dbuf_out.val1);
        // $dumpvars(0, dut.dbuf_out.val2);
        // $dumpvars(0, dut.dbuf_out.offset);

        // Reset everything for 3 clock cycles
        clk = 1'b0;
        rst = 1'b1;
        #30;
        rst = 1'b0;
        // Run for 2000 clock cycles 
        #20000;

        $display("Finished Test");
        $finish;
    end
endmodule

extra/verilog/waves.vcd
$date
	Wed Apr  1 15:24:22 2026
$end
$version
	Icarus Verilog
$end
$timescale
	1s
$end
$scope module test $end
$var reg 1 ! clk $end
$var reg 1 " rst $end
$scope module dut $end
$var wire 1 ! clk $end
$var wire 1 " rst $end
$var wire 32 # instruction_read_line [31:0] $end
$var wire 32 $ ins [31:0] $end
$var wire 32 % dout2 [31:0] $end
$var wire 32 & dout1 [31:0] $end
$var wire 32 ' debug_dbuf_val2 [31:0] $end
$var wire 32 ( debug_dbuf_val1 [31:0] $end
$var wire 32 ) debug_dbuf_pc [31:0] $end
$var wire 4 * debug_dbuf_op [3:0] $end
$var wire 32 + debug_dbuf_offset [31:0] $end
$var wire 4 , debug_dbuf_dr [3:0] $end
$var wire 32 - data_read_line [31:0] $end
$var wire 32 . alu_result [31:0] $end
$var reg 32 / PC [31:0] $end
$var reg 32 0 alu_val1 [31:0] $end
$var reg 32 1 alu_val2 [31:0] $end
$var reg 3 2 aluop [2:0] $end
$var reg 32 3 branch_target_line [31:0] $end
$var reg 1 4 branch_true $end
$var reg 32 5 data_write_dmem [31:0] $end
$var reg 144 6 dbuf_in [143:0] $end
$var reg 144 7 dbuf_out [143:0] $end
$var reg 4 8 dr [3:0] $end
$var reg 72 9 ebuf_in [71:0] $end
$var reg 72 : ebuf_out [71:0] $end
$var reg 64 ; fbuf_in [63:0] $end
$var reg 64 < fbuf_out [63:0] $end
$var reg 32 = fwd_val1 [31:0] $end
$var reg 32 > fwd_val2 [31:0] $end
$var reg 20 ? imm_wire [19:0] $end
$var reg 36 @ mbuf_in [35:0] $end
$var reg 36 A mbuf_out [35:0] $end
$var reg 4 B sr1 [3:0] $end
$var reg 4 C sr2 [3:0] $end
$var reg 1 D stall_now $end
$var reg 1 E we_dmem $end
$var reg 32 F write_reg_data [31:0] $end
$var reg 4 G write_reg_dest [3:0] $end
$scope module alu0 $end
$var wire 32 H a [31:0] $end
$var wire 32 I b [31:0] $end
$var wire 3 J op [2:0] $end
$var reg 32 K out [31:0] $end
$upscope $end
$scope module dmem $end
$var wire 16 L addr [15:0] $end
$var wire 1 ! clk $end
$var wire 32 M read_data [31:0] $end
$var wire 1 " rst $end
$var wire 1 E we $end
$var wire 32 N write_data [31:0] $end
$var parameter 80 O INIT $end
$var parameter 32 P SIZE $end
$scope begin $ivl_for_loop1 $end
$var integer 32 Q i [31:0] $end
$upscope $end
$upscope $end
$scope module imem $end
$var wire 16 R addr [15:0] $end
$var wire 1 ! clk $end
$var wire 32 S read_data [31:0] $end
$var wire 1 " rst $end
$var wire 1 T we $end
$var wire 32 U write_data [31:0] $end
$var parameter 80 V INIT $end
$var parameter 32 W SIZE $end
$scope begin $ivl_for_loop1 $end
$var integer 32 X i [31:0] $end
$upscope $end
$upscope $end
$scope module registers $end
$var wire 1 ! clk $end
$var wire 4 Y regno_read1 [3:0] $end
$var wire 4 Z regno_read2 [3:0] $end
$var wire 4 [ regno_write [3:0] $end
$var wire 1 " rst $end
$var wire 1 \ we $end
$var wire 32 ] write_data [31:0] $end
$var wire 32 ^ read_data2 [31:0] $end
$var wire 32 _ read_data1 [31:0] $end
$var parameter 32 ` NUM_REG $end
$scope function read_port $end
$var reg 4 a regno [3:0] $end
$upscope $end
$scope begin $ivl_for_loop0 $end
$var integer 32 b i [31:0] $end
$upscope $end
$upscope $end
$upscope $end
$scope begin $ivl_for_loop2 $end
$var integer 32 c i [31:0] $end
$upscope $end
$upscope $end
$scope module test $end
$scope module dut $end
$scope module registers $end
$var reg 32 d \registers[0] [31:0] $end
$upscope $end
$upscope $end
$upscope $end
$scope module test $end
$scope module dut $end
$scope module registers $end
$var reg 32 e \registers[1] [31:0] $end
$upscope $end
$upscope $end
$upscope $end
$scope module test $end
$scope module dut $end
$scope module registers $end
$var reg 32 f \registers[2] [31:0] $end
$upscope $end
$upscope $end
$upscope $end
$scope module test $end
$scope module dut $end
$scope module registers $end
$var reg 32 g \registers[3] [31:0] $end
$upscope $end
$upscope $end
$upscope $end
$scope module test $end
$scope module dut $end
$scope module registers $end
$var reg 32 h \registers[4] [31:0] $end
$upscope $end
$upscope $end
$upscope $end
$scope module test $end
$scope module dut $end
$scope module registers $end
$var reg 32 i \registers[5] [31:0] $end
$upscope $end
$upscope $end
$upscope $end
$scope module test $end
$scope module dut $end
$scope module registers $end
$var reg 32 j \registers[6] [31:0] $end
$upscope $end
$upscope $end
$upscope $end
$scope module test $end
$scope module dut $end
$scope module registers $end
$var reg 32 k \registers[7] [31:0] $end
$upscope $end
$upscope $end
$upscope $end
$scope module test $end
$scope module dut $end
$scope module registers $end
$var reg 32 l \registers[8] [31:0] $end
$upscope $end
$upscope $end
$upscope $end
$scope module test $end
$scope module dut $end
$scope module registers $end
$var reg 32 m \registers[9] [31:0] $end
$upscope $end
$upscope $end
$upscope $end
$scope module test $end
$scope module dut $end
$scope module registers $end
$var reg 32 n \registers[10] [31:0] $end
$upscope $end
$upscope $end
$upscope $end
$scope module test $end
$scope module dut $end
$scope module registers $end
$var reg 32 o \registers[11] [31:0] $end
$upscope $end
$upscope $end
$upscope $end
$scope module test $end
$scope module dut $end
$scope module registers $end
$var reg 32 p \registers[12] [31:0] $end
$upscope $end
$upscope $end
$upscope $end
$scope module test $end
$scope module dut $end
$scope module registers $end
$var reg 32 q \registers[13] [31:0] $end
$upscope $end
$upscope $end
$upscope $end
$scope module test $end
$scope module dut $end
$scope module registers $end
$var reg 32 r \registers[14] [31:0] $end
$upscope $end
$upscope $end
$upscope $end
$scope module test $end
$scope module dut $end
$scope module registers $end
$var reg 32 s \registers[15] [31:0] $end
$upscope $end
$upscope $end
$upscope $end
$enddefinitions $end
$comment Show the parameter values. $end
$dumpall
b10000 `
b10000000000000000 W
b101110001011100010111101110000011011110111011100101110011010000110010101111000 V
b10000000000000000 P
b101110001011100010111101110000011011110111011100101110011010000110010101111000 O
$end
#0
$dumpvars
bx s
bx r
bx q
bx p
bx o
bx n
bx m
bx l
bx k
bx j
bx i
bx h
bx g
bx f
bx e
bx d
b10000 c
b0 b
b0 a
b0 _
b0 ^
bx ]
1\
bx [
b0 Z
b0 Y
b10000000000000000 X
b0 U
0T
bx S
bx R
b10000000000000000 Q
bx N
bx M
bx L
bx K
b110 J
bx I
bx H
bx G
bx F
xE
xD
b0 C
b0 B
bx A
b0 @
b0 ?
bx >
bx =
bx <
bx ;
bx :
bx00000000000000000000000000000000000000000000000000000000000000000000 9
b0 8
bx 7
bx0000000000000000000000000000000000000000000000000000000000000000000000000000000000000000000000000000000000000000 6
bx 5
04
bx 3
b110 2
bx 1
bx 0
bx /
bx .
bx -
bx ,
bx +
bx *
bx )
bx (
bx '
b0 &
b0 %
b0 $
bx #
1"
0!
$end
#5
b10011101000000000000000000110101 #
b10011101000000000000000000110101 S
b10011101000000000000000000110101 -
b10011101000000000000000000110101 M
b0 .
b0 K
b110011101000000000000000000110101 ;
b0 R
b0 9
b0 3
b0 )
b0 *
b0 ,
b0 (
b0 '
b0 +
b0 5
b0 N
0E
b0 L
b0 F
b0 ]
b0 G
b0 [
b0 2
b0 J
b0 1
b0 I
b0 0
b0 H
b0 >
b0 =
b0 s
b0 r
b0 q
b0 p
b0 o
b0 n
b0 m
b0 l
b0 k
b0 j
b0 i
b0 h
b0 g
b0 f
b0 e
b0 d
b0 /
0D
b0 7
b0 :
b0 A
b10000 b
1!
#10
0!
#15
b0 6
b0 s
b0 r
b0 q
b0 p
b0 o
b0 n
b0 m
b0 l
b0 k
b0 j
b0 i
b0 h
b0 g
b0 f
b0 e
b0 d
b0 <
b10000 b
1!
#20
0!
#25
b0 s
b0 r
b0 q
b0 p
b0 o
b0 n
b0 m
b0 l
b0 k
b0 j
b0 i
b0 h
b0 g
b0 f
b0 e
b0 d
b10000 b
1!
#30
0!
0"
#35
b110101 ?
b1101 8
b10011101000000000000000000110101 $
b111101110100000000000000000000 #
b111101110100000000000000000000 S
b11001000000000000000000000000000000000000000000000000000000000000000000000000000000000000000000110101110100000000 6
b1000111101110100000000000000000000 ;
b1 R
b110011101000000000000000000110101 <
b1 /
1!
#40
0!
#45
b1101 a
b0 ?
b1101 B
b1101 Y
b10010011000000000000000000010000 #
b10010011000000000000000000010000 S
b111101110100000000000000000000 $
b110110 .
b110110 K
b1110010011000000000000000000010000 ;
b10 R
b100011000000000000000000000000000000000000000000000000000000000000000000000000000000000000000000000000110111010000 6
b100111010000000000000000000000000000000000000000000000000000000000110110 9
b110110 3
b110101 1
b110101 I
b1 0
b1 H
b1 )
b1001 *
b1101 ,
b110101 +
b10 /
b1000111101110100000000000000000000 <
b11001000000000000000000000000000000000000000000000000000000000000000000000000000000000000000000110101110100000000 7
1!
#50
0!
#55
b0 a
b10000 ?
b0 B
b0 Y
b11 8
b10010011000000000000000000010000 $
b110011001100000000000000000000 #
b110011001100000000000000000000 S
b110100000000000000000000000000110110 @
b110110 5
b110110 N
b1111010000000000000000000000000011011000000000000000000000000000000000 9
b10 3
b0 1
b0 I
b110110 0
b110110 H
b110110 =
b10 )
b11 *
b0 +
b111001000000000000000000000000000000000000000000000000000000000000000000000000000000000000000000010000001100000000 6
b10000110011001100000000000000000000 ;
b11 R
b100111010000000000000000000000000000000000000000000000000000000000110110 :
b100011000000000000000000000000000000000000000000000000000000000000000000000000000000000000000000000000110111010000 7
b1110010011000000000000000000010000 <
b11 /
1!
#60
0!
#65
b11 a
b0 ?
b11 B
b11 Y
b10010100000000000000000000001111 #
b10010100000000000000000000001111 S
b110011001100000000000000000000 $
b1010000000000000 -
b1010000000000000 M
b10011 .
b10011 K
b10110010100000000000000000000001111 ;
b100 R
b1000011000000000000000000000000000000000000000000000000000000000000000000000000000000000000000000000000001100110000 6
b100100110000000000000000000000000000000000000000000000000000000000010011 9
b10011 3
b11 )
b1001 *
b11 ,
b10000 +
b110100000000000000001010000000000000 @
b0 5
b0 N
b110110 L
b110110 F
b110110 ]
b1101 G
b1101 [
b10000 1
b10000 I
b11 0
b11 H
b0 =
b100 /
b10000110011001100000000000000000000 <
b111001000000000000000000000000000000000000000000000000000000000000000000000000000000000000000000010000001100000000 7
b1111010000000000000000000000000011011000000000000000000000000000000000 :
b110100000000000000000000000000110110 A
1!
#70
0!
#75
b0 a
b1111 ?
b0 B
b0 Y
b100 8
b10011101000000000000000000110101 -
b10011101000000000000000000110101 M
b10010100000000000000000000001111 $
b110100010000000000000000000000 #
b110100010000000000000000000000 S
b1010000000000000 F
b1010000000000000 ]
b1100000000000000000000000000010011 @
b10011 5
b10011 N
b0 L
b1100110000000000000000000000000001001100000000000000000000000000000000 9
b100 3
b0 1
b0 I
b10011 0
b10011 H
b10011 =
b100 )
b11 *
b0 +
b1011001000000000000000000000000000000000000000000000000000000000000000000000000000000000000000000001111010000000000 6
b11000110100010000000000000000000000 ;
b101 R
b110100000000000000001010000000000000 A
b100100110000000000000000000000000000000000000000000000000000000000010011 :
b1000011000000000000000000000000000000000000000000000000000000000000000000000000000000000000000000000000001100110000 7
b10110010100000000000000000000001111 <
b101 /
b110110 q
1!
#80
0!
#85
b100 a
b0 ?
b100 B
b100 Y
b10010001000000000000000000010100 #
b10010001000000000000000000010100 S
b110100010000000000000000000000 $
b10 -
b10 M
b10100 .
b10100 K
b11110010001000000000000000000010100 ;
b110 R
b1100011000000000000000000000000000000000000000000000000000000000000000000000000000000000000000000000000010001000000 6
b100101000000000000000000000000000000000000000000000000000000000000010100 9
b10100 3
b101 )
b1001 *
b100 ,
b1111 +
b1100000000000000000000000000000010 @
b0 5
b0 N
b10011 L
b10011 F
b10011 ]
b11 G
b11 [
b1111 1
b1111 I
b101 0
b101 H
b0 =
b1010000000000000 q
b110 /
b11000110100010000000000000000000000 <
b1011001000000000000000000000000000000000000000000000000000000000000000000000000000000000000000000001111010000000000 7
b1100110000000000000000000000000001001100000000000000000000000000000000 :
b1100000000000000000000000000010011 A
1!
#90
0!
#95
b0 a
b10100 ?
b0 B
b0 Y
b1 8
b10011101000000000000000000110101 -
b10011101000000000000000000110101 M
b10010001000000000000000000010100 $
b110000000000000000000000000 #
b110000000000000000000000000 S
b10 F
b10 ]
b10000000000000000000000000000010100 @
b10100 5
b10100 N
b0 L
b1101000000000000000000000000000001010000000000000000000000000000000000 9
b110 3
b0 1
b0 I
b10100 0
b10100 H
b10100 =
b110 )
b11 *
b0 +
b1111001000000000000000000000000000000000000000000000000000000000000000000000000000000000000000000010100000100000000 6
b100000000110000000000000000000000000 ;
b111 R
b1100000000000000000000000000000010 A
b100101000000000000000000000000000000000000000000000000000000000000010100 :
b1100011000000000000000000000000000000000000000000000000000000000000000000000000000000000000000000000000010001000000 7
b11110010001000000000000000000010100 <
b111 /
b10011 g
1!
#100
0!
#105
b0 ?
b110 8
b111000000000000000000000000 #
b111000000000000000000000000 S
b110000000000000000000000000 $
b1000 -
b1000 M
b11011 .
b11011 K
b100100000111000000000000000000000000 ;
b1000 R
b10000000000000000000000000000000000000000000000000000000000000000000000000000000000000000000000000000000011000000000 6
b100100010000000000000000000000000000000000000000000000000000000000011011 9
b11011 3
b111 )
b1001 *
b1 ,
b10100 +
b10000000000000000000000000000001000 @
b0 5
b0 N
b10100 L
b10100 F
b10100 ]
b100 G
b100 [
b10100 1
b10100 I
b111 0
b111 H
b0 =
b10 g
b1000 /
b100000000110000000000000000000000000 <
b1111001000000000000000000000000000000000000000000000000000000000000000000000000000000000000000000010100000100000000 7
b1101000000000000000000000000000001010000000000000000000000000000000000 :
b10000000000000000000000000000010100 A
1!
#110
0!
#115
b111 8
b10011101000000000000000000110101 -
b10011101000000000000000000110101 M
b0 .
b0 K
b111000000000000000000000000 $
b1000000000000000000000000000 #
b1000000000000000000000000000 S
b1000 F
b1000 ]
b100000000000000000000000000011011 @
b11011 5
b11011 N
b0 L
b1100000000000000000000000000000000000000000000000000000000000000000 9
b1000 3
b0 1
b0 I
b0 0
b0 H
b1000 )
b0 *
b110 ,
b0 +
b10010000000000000000000000000000000000000000000000000000000000000000000000000000000000000000000000000000011100000000 6
b101000001000000000000000000000000000 ;
b1001 R
b10000000000000000000000000000001000 A
b100100010000000000000000000000000000000000000000000000000000000000011011 :
b10000000000000000000000000000000000000000000000000000000000000000000000000000000000000000000000000000000011000000000 7
b100100000111000000000000000000000000 <
b1001 /
b10100 h
1!
#120
0!
#125
b1000 8
b100110011000000000000000000001 #
b100110011000000000000000000001 S
b1000000000000000000000000000 $
b101100100110011000000000000000000001 ;
b1010 R
b10100000000000000000000000000000000000000000000000000000000000000000000000000000000000000000000000000000100000000000 6
b1110000000000000000000000000000000000000000000000000000000000000000 9
b1001 3
b1001 )
b111 ,
b11000000000000000000000000000000000 @
b0 5
b0 N
b11011 F
b11011 ]
b1 G
b1 [
b1000 h
b1010 /
b101000001000000000000000000000000000 <
b10010000000000000000000000000000000000000000000000000000000000000000000000000000000000000000000000000000011100000000 7
b1100000000000000000000000000000000000000000000000000000000000000000 :
b100000000000000000000000000011011 A
1!
#130
0!
#135
b110 a
b1 ?
b110 B
b110 Y
b110 8
b100110011000000000000000000001 $
b100111011100000000000000000001 #
b100111011100000000000000000001 S
b0 F
b0 ]
b110 G
b110 [
b11100000000000000000000000000000000 @
b10000000000000000000000000000000000000000000000000000000000000000000 9
b1010 3
b1010 )
b1000 ,
b10110010000000000000000000000000000000000000000000000000000000000000000000000000000000000000000000000001011001100000 6
b110000100111011100000000000000000001 ;
b1011 R
b11000000000000000000000000000000000 A
b1110000000000000000000000000000000000000000000000000000000000000000 :
b10100000000000000000000000000000000000000000000000000000000000000000000000000000000000000000000000000000100000000000 7
b101100100110011000000000000000000001 <
b1011 /
b11011 e
1!
#140
0!
#145
b111 a
b111 B
b111 Y
b111 8
b1010110011100000000000000000001 #
b1010110011100000000000000000001 S
b100111011100000000000000000001 $
b1 .
b1 K
b110101010110011100000000000000000001 ;
b1100 R
b11000010000000000000000000000000000000000000000000000000000000000000000000000000000000000000000000000001011101110000 6
b1001100000000000000000000000000000000000000000000000000000000000000001 9
b1100 3
b1011 )
b10 *
b110 ,
b1 +
b100000000000000000000000000000000000 @
b111 G
b111 [
b1 1
b1 I
b0 j
b1100 /
b110000100111011100000000000000000001 <
b10110010000000000000000000000000000000000000000000000000000000000000000000000000000000000000000000000001011001100000 7
b10000000000000000000000000000000000000000000000000000000000000000000 :
b11100000000000000000000000000000000 A
1!
#150
0!
#155
b111 a
b111 C
b111 Z
b110 B
b110 Y
b0 8
b1010110011100000000000000000001 $
b1110000000000000000000000000000 #
b1110000000000000000000000000000 S
b1000 G
b1000 [
b11000000000000000000000000000000001 @
b1 5
b1 N
b1001110000000000000000000000000000000000000000000000000000000000000001 9
b1101 3
b1 1
b1 I
b1100 )
b111 ,
b11010101000000000000000000000000000000000000000000000000000000000000000000000000000000000000000000000001000001100111 6
b111001110000000000000000000000000000 ;
b1101 R
b100000000000000000000000000000000000 A
b1001100000000000000000000000000000000000000000000000000000000000000001 :
b11000010000000000000000000000000000000000000000000000000000000000000000000000000000000000000000000000001011101110000 7
b110101010110011100000000000000000001 <
b1101 /
b0 k
1!
#160
0!
